tang/serial test/my/top.v
module uart_tx (
    input clk,          
    output reg out      
);
    reg [7:0] data = 8'b0;
    reg ena = 1'b1;

    wire [9:0] datafull ;
    reg [3:0] countToTen = 4'b0;

    assign datafull= {1'b0 , data, 1'b1};

    always @(posedge clk)begin

        if (ena) begin
            out <= datafull[countToTen];
            if (countToTen == 4'd9)begin
                countToTen <= 4'b0;
            end
            else begin
                countToTen <= countToTen +4'b1 ;
            end
        end

        else begin
            out <= 1;
        end
    end
endmodule

tang/serial test/my/testbench.v
`timescale 1us / 1ns  // Use microseconds for timing

module tb_uart_tx;

    reg clk;
    wire out;

    // Instantiate the DUT
    uart_tx uut (
        .clk(clk),
        .out(out)
    );

    // Clock generation: 9600 Hz => period ≈ 104.1667 us
    initial begin
        clk = 0;
        forever #52.08 clk = ~clk;  // Half period for 9600 Hz (approx)
    end

    // Simulation duration and waveform output
    initial begin
        $dumpfile("uart_tx.vcd");
        $dumpvars(0, tb_uart_tx);
        #20000;  // Simulate for 20 ms
        $finish;
    end

endmodule

tang/serial test/my/uart_tx.vcd
$date
	Sun May 11 00:25:01 2025
$end
$version
	Icarus Verilog
$end
$timescale
	1ns
$end
$scope module tb_uart_tx $end
$var wire 1 ! out $end
$var reg 1 " clk $end
$scope module uut $end
$var wire 1 " clk $end
$var wire 10 # datafull [9:0] $end
$var reg 4 $ countToTen [3:0] $end
$var reg 8 % data [7:0] $end
$var reg 1 & ena $end
$var reg 1 ! out $end
$upscope $end
$upscope $end
$enddefinitions $end
$comment Show the parameter values. $end
$dumpall
$end
#0
$dumpvars
1&
b0 %
b0 $
b1 #
0"
x!
$end
#52080
b1 $
1!
1"
#104160
0"
#156240
b10 $
0!
1"
#208320
0"
#260400
b11 $
1"
#312480
0"
#364560
b100 $
1"
#416640
0"
#468720
b101 $
1"
#520800
0"
#572880
b110 $
1"
#624960
0"
#677040
b111 $
1"
#729120
0"
#781200
b1000 $
1"
#833280
0"
#885360
b1001 $
1"
#937440
0"
#989520
b0 $
1"
#1041600
0"
#1093680
b1 $
1!
1"
#1145760
0"
#1197840
b10 $
0!
1"
#1249920
0"
#1302000
b11 $
1"
#1354080
0"
#1406160
b100 $
1"
#1458240
0"
#1510320
b101 $
1"
#1562400
0"
#1614480
b110 $
1"
#1666560
0"
#1718640
b111 $
1"
#1770720
0"
#1822800
b1000 $
1"
#1874880
0"
#1926960
b1001 $
1"
#1979040
0"
#2031120
b0 $
1"
#2083200
0"
#2135280
b1 $
1!
1"
#2187360
0"
#2239440
b10 $
0!
1"
#2291520
0"
#2343600
b11 $
1"
#2395680
0"
#2447760
b100 $
1"
#2499840
0"
#2551920
b101 $
1"
#2604000
0"
#2656080
b110 $
1"
#2708160
0"
#2760240
b111 $
1"
#2812320
0"
#2864400
b1000 $
1"
#2916480
0"
#2968560
b1001 $
1"
#3020640
0"
#3072720
b0 $
1"
#3124800
0"
#3176880
b1 $
1!
1"
#3228960
0"
#3281040
b10 $
0!
1"
#3333120
0"
#3385200
b11 $
1"
#3437280
0"
#3489360
b100 $
1"
#3541440
0"
#3593520
b101 $
1"
#3645600
0"
#3697680
b110 $
1"
#3749760
0"
#3801840
b111 $
1"
#3853920
0"
#3906000
b1000 $
1"
#3958080
0"
#4010160
b1001 $
1"
#4062240
0"
#4114320
b0 $
1"
#4166400
0"
#4218480
b1 $
1!
1"
#4270560
0"
#4322640
b10 $
0!
1"
#4374720
0"
#4426800
b11 $
1"
#4478880
0"
#4530960
b100 $
1"
#4583040
0"
#4635120
b101 $
1"
#4687200
0"
#4739280
b110 $
1"
#4791360
0"
#4843440
b111 $
1"
#4895520
0"
#4947600
b1000 $
1"
#4999680
0"
#5051760
b1001 $
1"
#5103840
0"
#5155920
b0 $
1"
#5208000
0"
#5260080
b1 $
1!
1"
#5312160
0"
#5364240
b10 $
0!
1"
#5416320
0"
#5468400
b11 $
1"
#5520480
0"
#5572560
b100 $
1"
#5624640
0"
#5676720
b101 $
1"
#5728800
0"
#5780880
b110 $
1"
#5832960
0"
#5885040
b111 $
1"
#5937120
0"
#5989200
b1000 $
1"
#6041280
0"
#6093360
b1001 $
1"
#6145440
0"
#6197520
b0 $
1"
#6249600
0"
#6301680
b1 $
1!
1"
#6353760
0"
#6405840
b10 $
0!
1"
#6457920
0"
#6510000
b11 $
1"
#6562080
0"
#6614160
b100 $
1"
#6666240
0"
#6718320
b101 $
1"
#6770400
0"
#6822480
b110 $
1"
#6874560
0"
#6926640
b111 $
1"
#6978720
0"
#7030800
b1000 $
1"
#7082880
0"
#7134960
b1001 $
1"
#7187040
0"
#7239120
b0 $
1"
#7291200
0"
#7343280
b1 $
1!
1"
#7395360
0"
#7447440
b10 $
0!
1"
#7499520
0"
#7551600
b11 $
1"
#7603680
0"
#7655760
b100 $
1"
#7707840
0"
#7759920
b101 $
1"
#7812000
0"
#7864080
b110 $
1"
#7916160
0"
#7968240
b111 $
1"
#8020320
0"
#8072400
b1000 $
1"
#8124480
0"
#8176560
b1001 $
1"
#8228640
0"
#8280720
b0 $
1"
#8332800
0"
#8384880
b1 $
1!
1"
#8436960
0"
#8489040
b10 $
0!
1"
#8541120
0"
#8593200
b11 $
1"
#8645280
0"
#8697360
b100 $
1"
#8749440
0"
#8801520
b101 $
1"
#8853600
0"
#8905680
b110 $
1"
#8957760
0"
#9009840
b111 $
1"
#9061920
0"
#9114000
b1000 $
1"
#9166080
0"
#9218160
b1001 $
1"
#9270240
0"
#9322320
b0 $
1"
#9374400
0"
#9426480
b1 $
1!
1"
#9478560
0"
#9530640
b10 $
0!
1"
#9582720
0"
#9634800
b11 $
1"
#9686880
0"
#9738960
b100 $
1"
#9791040
0"
#9843120
b101 $
1"
#9895200
0"
#9947280
b110 $
1"
#9999360
0"
#10051440
b111 $
1"
#10103520
0"
#10155600
b1000 $
1"
#10207680
0"
#10259760
b1001 $
1"
#10311840
0"
#10363920
b0 $
1"
#10416000
0"
#10468080
b1 $
1!
1"
#10520160
0"
#10572240
b10 $
0!
1"
#10624320
0"
#10676400
b11 $
1"
#10728480
0"
#10780560
b100 $
1"
#10832640
0"
#10884720
b101 $
1"
#10936800
0"
#10988880
b110 $
1"
#11040960
0"
#11093040
b111 $
1"
#11145120
0"
#11197200
b1000 $
1"
#11249280
0"
#11301360
b1001 $
1"
#11353440
0"
#11405520
b0 $
1"
#11457600
0"
#11509680
b1 $
1!
1"
#11561760
0"
#11613840
b10 $
0!
1"
#11665920
0"
#11718000
b11 $
1"
#11770080
0"
#11822160
b100 $
1"
#11874240
0"
#11926320
b101 $
1"
#11978400
0"
#12030480
b110 $
1"
#12082560
0"
#12134640
b111 $
1"
#12186720
0"
#12238800
b1000 $
1"
#12290880
0"
#12342960
b1001 $
1"
#12395040
0"
#12447120
b0 $
1"
#12499200
0"
#12551280
b1 $
1!
1"
#12603360
0"
#12655440
b10 $
0!
1"
#12707520
0"
#12759600
b11 $
1"
#12811680
0"
#12863760
b100 $
1"
#12915840
0"
#12967920
b101 $
1"
#13020000
0"
#13072080
b110 $
1"
#13124160
0"
#13176240
b111 $
1"
#13228320
0"
#13280400
b1000 $
1"
#13332480
0"
#13384560
b1001 $
1"
#13436640
0"
#13488720
b0 $
1"
#13540800
0"
#13592880
b1 $
1!
1"
#13644960
0"
#13697040
b10 $
0!
1"
#13749120
0"
#13801200
b11 $
1"
#13853280
0"
#13905360
b100 $
1"
#13957440
0"
#14009520
b101 $
1"
#14061600
0"
#14113680
b110 $
1"
#14165760
0"
#14217840
b111 $
1"
#14269920
0"
#14322000
b1000 $
1"
#14374080
0"
#14426160
b1001 $
1"
#14478240
0"
#14530320
b0 $
1"
#14582400
0"
#14634480
b1 $
1!
1"
#14686560
0"
#14738640
b10 $
0!
1"
#14790720
0"
#14842800
b11 $
1"
#14894880
0"
#14946960
b100 $
1"
#14999040
0"
#15051120
b101 $
1"
#15103200
0"
#15155280
b110 $
1"
#15207360
0"
#15259440
b111 $
1"
#15311520
0"
#15363600
b1000 $
1"
#15415680
0"
#15467760
b1001 $
1"
#15519840
0"
#15571920
b0 $
1"
#15624000
0"
#15676080
b1 $
1!
1"
#15728160
0"
#15780240
b10 $
0!
1"
#15832320
0"
#15884400
b11 $
1"
#15936480
0"
#15988560
b100 $
1"
#16040640
0"
#16092720
b101 $
1"
#16144800
0"
#16196880
b110 $
1"
#16248960
0"
#16301040
b111 $
1"
#16353120
0"
#16405200
b1000 $
1"
#16457280
0"
#16509360
b1001 $
1"
#16561440
0"
#16613520
b0 $
1"
#16665600
0"
#16717680
b1 $
1!
1"
#16769760
0"
#16821840
b10 $
0!
1"
#16873920
0"
#16926000
b11 $
1"
#16978080
0"
#17030160
b100 $
1"
#17082240
0"
#17134320
b101 $
1"
#17186400
0"
#17238480
b110 $
1"
#17290560
0"
#17342640
b111 $
1"
#17394720
0"
#17446800
b1000 $
1"
#17498880
0"
#17550960
b1001 $
1"
#17603040
0"
#17655120
b0 $
1"
#17707200
0"
#17759280
b1 $
1!
1"
#17811360
0"
#17863440
b10 $
0!
1"
#17915520
0"
#17967600
b11 $
1"
#18019680
0"
#18071760
b100 $
1"
#18123840
0"
#18175920
b101 $
1"
#18228000
0"
#18280080
b110 $
1"
#18332160
0"
#18384240
b111 $
1"
#18436320
0"
#18488400
b1000 $
1"
#18540480
0"
#18592560
b1001 $
1"
#18644640
0"
#18696720
b0 $
1"
#18748800
0"
#18800880
b1 $
1!
1"
#18852960
0"
#18905040
b10 $
0!
1"
#18957120
0"
#19009200
b11 $
1"
#19061280
0"
#19113360
b100 $
1"
#19165440
0"
#19217520
b101 $
1"
#19269600
0"
#19321680
b110 $
1"
#19373760
0"
#19425840
b111 $
1"
#19477920
0"
#19530000
b1000 $
1"
#19582080
0"
#19634160
b1001 $
1"
#19686240
0"
#19738320
b0 $
1"
#19790400
0"
#19842480
b1 $
1!
1"
#19894560
0"
#19946640
b10 $
0!
1"
