tang/UART_TX/src/UART_TX.v
module UART_TX (
    input clk,
    input [7:0] data,
    input send,
    input load,
    input rst,
    output reg tx
);

    reg [1:0] currentState= 2'b0;
    reg [9:0] dataShift;
    reg [3:0] dataShiftCount;

    parameter freq = 27000000;
    parameter baud=   3000000;
    localparam waitClocks = freq/baud;
    reg [7:0] waitClockCount ; 

    localparam _Idle = 2'h0;
    localparam _Send = 2'h1;
    localparam _Wait = 2'h2;

    always @(posedge clk or posedge rst)begin

        if (rst) begin 
            dataShiftCount <= 0;
            waitClockCount <= 0;
            dataShift <= {10{1'b1}};
            tx <= 1;
            currentState <= _Idle;
        end
        else if(load) begin 
            dataShiftCount <= 0;
            waitClockCount <= 0;
            dataShift <= {1'b1, data, 1'b0 } ;
        end

        else begin
            case(currentState)

            _Idle:begin
                tx <= 1;
                currentState <= send?_Send:_Idle ;
            end

            _Send: begin
                tx <= dataShift[0];
                currentState <= _Wait ;
                
            end

            _Wait : begin
                waitClockCount <= waitClockCount + 1'b1 ;
                if (waitClockCount== waitClocks-2) begin
                    waitClockCount <= 8'b0;
                    dataShiftCount <= dataShiftCount + 1'b1 ;
                    dataShift <= {1'b1, dataShift[9:1]};
                    if (dataShiftCount == 10 )begin
                        dataShiftCount <= 4'b0;

                        currentState <= _Idle;

                    end
                    else begin
                        currentState <= _Send;
                    end
                end
                else currentState <= _Wait;
            end
            endcase
        end
    end

    
endmodule

tang/UART_TX/src/bench.v
`timescale 1ns / 1ps

module UART_TX_tb;

    reg clk = 0;
    reg load = 0;
    reg send = 0;
    reg [7:0] data = 8'h41; // 'A'
    wire tx;

    // Instantiate your UART_TX with slower baud for easier debugging
    UART_TX #(
        .freq(4),  // 100 MHz clock for simulation
        .baud(2)
    ) uut (
        .clk(clk),
        .rst(rst),
        .load(load),
        .send(send),
        .data(data),
        .tx(tx)
    );

    // Clock generation: 10 ns period => 100 MHz
    always #1 clk = ~clk;

    initial begin
        $dumpfile("UART_TX_tb.vcd");
        $dumpvars(0, UART_TX_tb);


        // Wait some clocks
        #3;

        // Send one byte 'A'
        load = 1;
        send = 0;
        #2;       // 1 clock cycle pulse at 100MHz = 10ns
        load = 0;
        send =1 ;

        // Wait enough time for full frame to send (1 start + 8 data + 1 stop bits)
        // At 115200 baud, bit period ~ 8.68 us
        // Total frame = 10 bits * 8.68 us = 86.8 us
        #100;  // 100 us wait

        // Send another byte 'B'
        data = 8'h42;  // 'B'
        load = 1;
        send = 1;
        #10;
        load = 0;
        send = 0;

        #100_000;

        $finish;
    end

endmodule

tang/UART_TX/src/UART_TX_tb.vcd
$date
	Fri May 16 03:36:35 2025
$end
$version
	Icarus Verilog
$end
$timescale
	1ps
$end
$scope module UART_TX_tb $end
$var wire 1 ! rst $end
$var wire 1 " tx $end
$var reg 1 # clk $end
$var reg 8 $ data [7:0] $end
$var reg 1 % load $end
$var reg 1 & send $end
$scope module uut $end
$var wire 1 # clk $end
$var wire 8 ' data [7:0] $end
$var wire 1 % load $end
$var wire 1 ! rst $end
$var wire 1 & send $end
$var parameter 2 ( _Idle $end
$var parameter 2 ) _Send $end
$var parameter 2 * _Wait $end
$var parameter 32 + baud $end
$var parameter 32 , freq $end
$var parameter 32 - waitClocks $end
$var reg 2 . currentState [1:0] $end
$var reg 10 / dataShift [9:0] $end
$var reg 4 0 dataShiftCount [3:0] $end
$var reg 1 " tx $end
$var reg 8 1 waitClockCount [7:0] $end
$upscope $end
$upscope $end
$enddefinitions $end
$comment Show the parameter values. $end
$dumpall
b10 -
b100 ,
b10 +
b10 *
b1 )
b0 (
$end
#0
$dumpvars
bx 1
bx 0
bx /
b0 .
b1000001 '
0&
0%
b1000001 $
0#
x"
z!
$end
#1000
1#
#2000
0#
#3000
b1010000010 /
b0 1
b0 0
1#
1%
#4000
0#
#5000
b1 .
1"
1#
1&
0%
#6000
0#
#7000
b10 .
0"
1#
#8000
0#
#9000
b1 .
b1101000001 /
b1 0
b0 1
1#
#10000
0#
#11000
b10 .
1"
1#
#12000
0#
#13000
b1 .
b1110100000 /
b10 0
b0 1
1#
#14000
0#
#15000
b10 .
0"
1#
#16000
0#
#17000
b1 .
b1111010000 /
b11 0
b0 1
1#
#18000
0#
#19000
b10 .
1#
#20000
0#
#21000
b1 .
b1111101000 /
b100 0
b0 1
1#
#22000
0#
#23000
b10 .
1#
#24000
0#
#25000
b1 .
b1111110100 /
b101 0
b0 1
1#
#26000
0#
#27000
b10 .
1#
#28000
0#
#29000
b1 .
b1111111010 /
b110 0
b0 1
1#
#30000
0#
#31000
b10 .
1#
#32000
0#
#33000
b1 .
b1111111101 /
b111 0
b0 1
1#
#34000
0#
#35000
b10 .
1"
1#
#36000
0#
#37000
b1 .
b1111111110 /
b1000 0
b0 1
1#
#38000
0#
#39000
b10 .
0"
1#
#40000
0#
#41000
b1 .
b1111111111 /
b1001 0
b0 1
1#
#42000
0#
#43000
b10 .
1"
1#
#44000
0#
#45000
b1 .
b1010 0
b0 1
1#
#46000
0#
#47000
b10 .
1#
#48000
0#
#49000
b0 .
b0 0
b0 1
1#
#50000
0#
#51000
b1 .
1#
#52000
0#
#53000
b10 .
1#
#54000
0#
#55000
b1 .
b1 0
b0 1
1#
#56000
0#
#57000
b10 .
1#
#58000
0#
#59000
b1 .
b10 0
b0 1
1#
#60000
0#
#61000
b10 .
1#
#62000
0#
#63000
b1 .
b11 0
b0 1
1#
#64000
0#
#65000
b10 .
1#
#66000
0#
#67000
b1 .
b100 0
b0 1
1#
#68000
0#
#69000
b10 .
1#
#70000
0#
#71000
b1 .
b101 0
b0 1
1#
#72000
0#
#73000
b10 .
1#
#74000
0#
#75000
b1 .
b110 0
b0 1
1#
#76000
0#
#77000
b10 .
1#
#78000
0#
#79000
b1 .
b111 0
b0 1
1#
#80000
0#
#81000
b10 .
1#
#82000
0#
#83000
b1 .
b1000 0
b0 1
1#
#84000
0#
#85000
b10 .
1#
#86000
0#
#87000
b1 .
b1001 0
b0 1
1#
#88000
0#
#89000
b10 .
1#
#90000
0#
#91000
b1 .
b1010 0
b0 1
1#
#92000
0#
#93000
b10 .
1#
#94000
0#
#95000
b0 .
b0 0
b0 1
1#
#96000
0#
#97000
b1 .
1#
#98000
0#
#99000
b10 .
1#
#100000
0#
#101000
b1 .
b1 0
b0 1
1#
#102000
0#
#103000
b10 .
1#
#104000
0#
#105000
b1010000100 /
b0 0
1#
1%
b1000010 $
b1000010 '
#106000
0#
#107000
1#
#108000
0#
#109000
1#
#110000
0#
#111000
1#
#112000
0#
#113000
1#
#114000
0#
#115000
1#
0&
0%
